optimesh/__init__.py
optimesh/_helpers.py
optimesh/_main.py
optimesh/laplace.py
optimesh/_plot/__init__.py
optimesh/_plot/figure.py
optimesh/_plot/helpers.py
optimesh/_plot/hist.py
optimesh/_plot/subplot.py
optimesh/cli/__init__.py
optimesh/cli/_info.py
optimesh/cli/_main.py
optimesh/cpt/__init__.py
optimesh/cpt/fixed_point.py
optimesh/cpt/linear_solve.py
optimesh/cpt/quasi_newton.py
optimesh/cvt/__init__.py
optimesh/cvt/_helpers.py
optimesh/cvt/block_diagonal.py
optimesh/cvt/full.py
optimesh/cvt/lloyd.py
optimesh/odt/__init__.py
optimesh/odt/_nonlinear.py
optimesh/odt/fixed_point.py
optimesh-0.12.1.dist-info/METADATA
optimesh-0.12.1.dist-info/WHEEL
optimesh-0.12.1.dist-info/entry_points.txt
optimesh-0.12.1.dist-info/top_level.txt
optimesh-0.12.1.dist-info/RECORD
