Metadata-Version: 2.4
Name: optimesh
Version: 0.12.1
Summary: Mesh optimization/smoothing
Author-email: Nico Schlömer <nico.schloemer@gmail.com>
License-Expression: LicenseRef-Proprietary
Project-URL: Homepage, https://github.com/meshpro/optimesh
Project-URL: Issues, https://github.com/meshpro/optimesh/issues
Keywords: engineering,mathematics,mesh,mesh generation,optimization,physics
Classifier: Development Status :: 5 - Production/Stable
Classifier: Intended Audience :: Science/Research
Classifier: Operating System :: OS Independent
Classifier: Programming Language :: Python :: 3 :: Only
Classifier: Programming Language :: Python :: 3.10
Classifier: Programming Language :: Python :: 3.11
Classifier: Programming Language :: Python :: 3.12
Classifier: Programming Language :: Python :: 3.13
Classifier: Topic :: Scientific/Engineering
Classifier: Topic :: Utilities
Requires-Python: >=3.10
Requires-Dist: meshio>=5
Requires-Dist: meshplex<0.22,>=0.21.1
Requires-Dist: npx
Requires-Dist: numpy>=2
Requires-Dist: rich-argparse
Requires-Dist: scipy
Requires-Dist: stonefish-license-manager>=0.5.24
Requires-Dist: stonefish_runtime>=0.3.3
